CHANGELOG.rst
LICENSE.txt
MANIFEST.in
README.md
setup.cfg
setup.py
django_social_share_settings/__init__.py
django_social_share_settings/admin.py
django_social_share_settings/models.py
django_social_share_settings/urls.py
django_social_share_settings/views.py
django_social_share_settings.egg-info/PKG-INFO
django_social_share_settings.egg-info/SOURCES.txt
django_social_share_settings.egg-info/dependency_links.txt
django_social_share_settings.egg-info/not-zip-safe
django_social_share_settings.egg-info/requires.txt
django_social_share_settings.egg-info/top_level.txt
django_social_share_settings/migrations/0001_initial.py
django_social_share_settings/migrations/0002_auto__add_socialsharetrack.py
django_social_share_settings/migrations/__init__.py
django_social_share_settings/static/django_social_share_settings/css/sticky.css
django_social_share_settings/static/django_social_share_settings/css/sticky.min.css
django_social_share_settings/static/django_social_share_settings/js/sticky.jqueryplugin.js
django_social_share_settings/templatetags/__init__.py
django_social_share_settings/templatetags/social_share_settings_tags.py