Metadata-Version: 1.1
Name: django-social-share-settings
Version: 0.2
Summary: Model and front end library for choosing and integrating social media share widgets.
Home-page: https://github.com/ninapavlich/django-social-share-settings
Author: Nina Pavlich
Author-email: nina@cgparntersllc.com
License: BSD
Platform: UNKNOWN
Classifier: Development Status :: 5 - Production/Stable
Classifier: Environment :: Web Environment
Classifier: Framework :: Django
Classifier: Intended Audience :: Developers
Classifier: License :: OSI Approved
Classifier: Operating System :: OS Independent
Classifier: Programming Language :: Python
